streamer/__init__.py
streamer/__main__.py
streamer-0.3.dist-info/LICENCE.txt
streamer-0.3.dist-info/METADATA
streamer-0.3.dist-info/WHEEL
streamer-0.3.dist-info/entry_points.txt
streamer-0.3.dist-info/top_level.txt
streamer-0.3.dist-info/RECORD
