Metadata-Version: 2.1
Name: streamer
Version: 0.3
Summary: Stream movies directly from torrent without downloading
Home-page: https://github.com/unamdev0/streamer
Author: Udit Namdev
Author-email: unamdev0@gmail.com
License: MIT
Keywords: Torrent,Stream,Movies,Series,Streamer,Magnet link,utorrent,piratebay,yify
Platform: UNKNOWN
Classifier: Programming Language :: Python :: 3
Classifier: License :: OSI Approved :: MIT License
Classifier: Operating System :: OS Independent
Requires-Dist: BeautifulSoup4
Requires-Dist: requests
